orr_optimizer/ORR.py
orr_optimizer/__init__.py
orr_optimizer/dynamic_cat.py
orr_optimizer/graph_theory.py
orr_optimizer/metal.py
orr_optimizer/orr_cat.py
orr_optimizer/orr_mkm.py
orr_optimizer/sim_anneal.py
ORR_Optimization-0.2.dist-info/LICENSE
ORR_Optimization-0.2.dist-info/METADATA
ORR_Optimization-0.2.dist-info/WHEEL
ORR_Optimization-0.2.dist-info/top_level.txt
ORR_Optimization-0.2.dist-info/RECORD
