Metadata-Version: 2.1
Name: ORR-Optimization
Version: 0.2
Summary: Catalyst structure optimization for the oxygen reduction reaction on Pt and Au
Home-page: https://github.com/VlachosGroup/ORR-Optimization
Author: Marcel Nunez
Author-email: mpnunez28@gmail.com
License: UNKNOWN
Platform: UNKNOWN
Classifier: Programming Language :: Python :: 3
Classifier: License :: OSI Approved :: MIT License
Classifier: Operating System :: OS Independent
Requires-Dist: ase
Requires-Dist: numpy
Requires-Dist: scipy
Requires-Dist: matplotlib
Requires-Dist: pandas
